feebee/__init__.py
feebee/config.py
feebee/exceptions.py
feebee/feebee.py
feebee/logging.py
feebee/sqlite_keywords.txt
feebee/util.py
tests/__init__.py
tests/test_core.py
feebee-0.8.8.dist-info/METADATA
feebee-0.8.8.dist-info/WHEEL
feebee-0.8.8.dist-info/top_level.txt
feebee-0.8.8.dist-info/RECORD
