Metadata-Version: 2.1
Name: feebee
Version: 0.8.8
Summary: A data wrangling tool
Home-page: https://github.com/nalssee/feebee.git
Author: nalssee
Author-email: jinisrolling@gmail.com
License: MIT
Platform: UNKNOWN
Requires-Dist: openpyxl (>=2.5.12)
Requires-Dist: sas7bdat (>=2.0.7)
Requires-Dist: psutil (>=5.4.3)
Requires-Dist: graphviz (>=0.8.2)
Requires-Dist: pathos (>=0.2.2.1)
Requires-Dist: xlrd (>=0.9.0)
Requires-Dist: more-itertools (>=5.0.0)
Requires-Dist: coloredlogs (>=10.0)
Requires-Dist: tqdm (>=4.29.1)
Requires-Dist: statsmodels (==0.10.1)
Requires-Dist: statsmodels
Requires-Dist: pandas
